serial_tcp_clients-2.0.1.dev0.dist-info/DESCRIPTION.rst
serial_tcp_clients-2.0.1.dev0.dist-info/METADATA
serial_tcp_clients-2.0.1.dev0.dist-info/RECORD
serial_tcp_clients-2.0.1.dev0.dist-info/WHEEL
serial_tcp_clients-2.0.1.dev0.dist-info/metadata.json
serial_tcp_clients-2.0.1.dev0.dist-info/top_level.txt
serialtcp/__init__.py
serialtcp/__main__.py
serialtcp/client.py
serialtcp/serial_port.py
serialtcp/server.py
serialtcp/tcp_server.py
serialtcp/tpc_server.py
