Metadata-Version: 2.0
Name: serial-tcp-clients
Version: 2.0.1.dev0
Summary: share serial device through tcp connections
Home-page: https://github.com/maslovw/serial_tcp_clients
Author: maslovw
Author-email: serialtcp@maslovw.com
License: MIT
Keywords: serial com port tcp server socket
Platform: UNKNOWN
Requires-Python: ~=3.5
Requires-Dist: pyserial (>=3.3)
